exxec/__init__.py
exxec/acp_provider/__init__.py
exxec/acp_provider/process_manager.py
exxec/acp_provider/provider.py
exxec/base.py
exxec/beam_provider/__init__.py
exxec/beam_provider/helpers.py
exxec/beam_provider/process_manager.py
exxec/beam_provider/provider.py
exxec/daytona_provider/__init__.py
exxec/daytona_provider/helpers.py
exxec/daytona_provider/process_manager.py
exxec/daytona_provider/provider.py
exxec/daytona_provider/pty_manager.py
exxec/docker_provider/__init__.py
exxec/docker_provider/provider.py
exxec/docker_provider/pty_manager.py
exxec/e2b_provider/__init__.py
exxec/e2b_provider/process_manager.py
exxec/e2b_provider/provider.py
exxec/e2b_provider/pty_manager.py
exxec/events.py
exxec/local_provider/__init__.py
exxec/local_provider/provider.py
exxec/local_provider/pty_manager.py
exxec/local_provider/utils.py
exxec/log.py
exxec/microsandbox_provider/__init__.py
exxec/microsandbox_provider/provider.py
exxec/mock_provider/__init__.py
exxec/mock_provider/process_manager.py
exxec/mock_provider/provider.py
exxec/mock_provider/pty_manager.py
exxec/modal_provider/__init__.py
exxec/modal_provider/provider.py
exxec/modal_provider/pty_manager.py
exxec/models.py
exxec/parse_output.py
exxec/pep723.py
exxec/process_manager.py
exxec/pty_manager.py
exxec/py.typed
exxec/pyodide_provider/__init__.py
exxec/pyodide_provider/filesystem.py
exxec/pyodide_provider/provider.py
exxec/pyodide_provider/pyodide_server.ts
exxec/remote_callable.py
exxec/srt_provider/__init__.py
exxec/srt_provider/config.py
exxec/srt_provider/provider.py
exxec/ssh_provider/__init__.py
exxec/ssh_provider/provider.py
exxec/ssh_provider/pty_manager.py
exxec/vercel_provider/__init__.py
exxec/vercel_provider/process_manager.py
exxec/vercel_provider/provider.py
exxec_config/__init__.py
exxec_config/configs.py
exxec_config/py.typed
exxec_config/srt_sandbox_config.py
exxec-0.3.6.dist-info/licenses/LICENSE
exxec-0.3.6.dist-info/WHEEL
exxec-0.3.6.dist-info/METADATA
exxec-0.3.6.dist-info/RECORD
