Metadata-Version: 2.4
Name: exxec
Version: 0.3.6
Summary: Execution environments
Keywords: 
Author: Philipp Temminghoff
Author-email: Philipp Temminghoff <philipptemminghoff@googlemail.com>
License-Expression: MIT
License-File: LICENSE
Classifier: Development Status :: 4 - Beta
Classifier: Framework :: Pydantic
Classifier: Framework :: Pydantic :: 2
Classifier: Intended Audience :: Developers
Classifier: Operating System :: OS Independent
Classifier: Programming Language :: Python :: 3
Classifier: Programming Language :: Python :: 3 :: Only
Classifier: Programming Language :: Python :: 3.12
Classifier: Programming Language :: Python :: 3.13
Classifier: Programming Language :: Python :: 3.14
Classifier: Topic :: Documentation
Classifier: Topic :: Software Development
Classifier: Topic :: Utilities
Classifier: Typing :: Typed
Requires-Dist: anyenv>=1.11.6
Requires-Dist: ptyprocess>=0.7.0
Requires-Dist: pydantic
Requires-Dist: schemez
Requires-Dist: upathtools>=1.9.0
Requires-Dist: beam-client>=0.2.187 ; extra == 'beam'
Requires-Dist: daytona ; python_full_version < '3.14' and extra == 'daytona'
Requires-Dist: testcontainers ; extra == 'docker'
Requires-Dist: e2b-code-interpreter ; extra == 'e2b'
Requires-Dist: fastmcp ; extra == 'mcp'
Requires-Dist: mcp-run-python ; extra == 'mcp'
Requires-Dist: microsandbox ; extra == 'microsandbox'
Requires-Dist: modal ; extra == 'modal'
Requires-Dist: asyncssh ; extra == 'ssh'
Requires-Dist: sshfs ; extra == 'ssh'
Requires-Dist: vercel ; extra == 'vercel'
Requires-Python: >=3.13
Project-URL: Code coverage, https://app.codecov.io/gh/phil65/exxec
Project-URL: Discussions, https://github.com/phil65/exxec/discussions
Project-URL: Documentation, https://phil65.github.io/exxec/
Project-URL: Issues, https://github.com/phil65/exxec/issues
Project-URL: Source, https://github.com/phil65/exxec
Provides-Extra: beam
Provides-Extra: daytona
Provides-Extra: docker
Provides-Extra: e2b
Provides-Extra: mcp
Provides-Extra: microsandbox
Provides-Extra: modal
Provides-Extra: ssh
Provides-Extra: vercel
